cvai_logger/__init__.py
cvai_logger/logger.py
cvai_logger-0.1.4.dist-info/WHEEL
cvai_logger-0.1.4.dist-info/METADATA
cvai_logger-0.1.4.dist-info/RECORD
