Metadata-Version: 2.1
Name: cvai-logger
Version: 0.1.4
Summary: ClearVision AI logger
Author: Gautham Reddy
Author-email: gauthamv93@yahoo.com
Requires-Python: >=3.6,<4.0
Classifier: Programming Language :: Python :: 3
Classifier: Programming Language :: Python :: 3.10
Classifier: Programming Language :: Python :: 3.6
Classifier: Programming Language :: Python :: 3.7
Classifier: Programming Language :: Python :: 3.8
Classifier: Programming Language :: Python :: 3.9
Requires-Dist: pytz (>=2022.1,<2023.0)
